[
  {
    "id": "carlos-vives-2025",
    "title": "BBVA - ESTRELLAS",
    "artists": ["Carlos Vives"],
    "city": "Lima",
    "venue": "Estadio Nacional",
    "datetime": "2025-12-14T21:00:00-03:00",
    "priceFrom": 85,
    "currency": "USD",
    "stock": 20000,
    "soldOut": true,
    "popularity": 100,
    "images": ["images/image1.jpg"],
    "policies": {"age":"Todas las edades","refund":"Política del organizador / vendedor"},
    "description": "El concierto de Carlos Vives en Lima, parte de la gira 'BBVA - ESTRELLAS', promete ser una noche inolvidable llena de éxitos y energía.",
    "coordinates": [-77.033722, -12.067278] 
  },
  {
    "id": "Lil Silvio y El Vega",
    "title": "Lil Silvio y El Vega en Cajamarca",
    "artists": ["Lil Silvio y El Vega"],
    "city": "Cajamarca",
    "venue": "La herradura",
    "datetime": "2025-10-7T20:00:00-05:00",
    "priceFrom": 15,
    "currency": "USD",
    "stock": 2500,
    "soldOut": true,
    "popularity": 88,
    "images": ["images/image2.jpg"],
    "policies": {"age":"Todas las edades","refund":"Política del organizador / vendedor"},
    "description": "Parte de la gira 'La Nueva Ola del Reggaeton Peruano', Lil Silvio y El Vega llegan a Cajamarca para una noche llena de ritmo y sabor.",
    "coordinates": [-77.033722, -12.067278] 
  },
  {
    "id": "trueno-Perú",
    "title": "TRUENO EN LIMA",
    "artists": ["trueno"],
    "city": "Lima",
    "venue": "Costa 21",
    "datetime": "2025-08-15T20:00:00-05:00",
    "priceFrom": 50,
    "currency": "USD",
    "stock": 20000,
    "soldOut": true,
    "popularity": 80,
    "images": ["images/image3.jpg"],
    "policies": {"age":"Todas las edades","refund":"No aplica, evento pasado"},
    "description": "Uno de los conciertos más recordados de trueno en Perú, donde el artista argentino deleitó a sus fans con una actuación enérgica y llena de pasión.",
    "coordinates": [-77.0796283, -12.0964151] 
  },
  {
    "id": "Axel-2025",
    "title": "Axel-tour-2025",
    "artists": ["Axel"],
    "city": "Arequipa",
    "venue": "Teatro Fénix",
    "datetime": "2025-10-25T20:00:00-03:00",
    "priceFrom": 20,
    "currency": "USD",
    "stock": 9500,
    "soldOut": false,
    "popularity": 70,
    "images": ["images/image4.jpg"],
    "policies": {"age":"Todas las edades","refund":"Política del organizador / vendedor"},
    "description": "El artista Axel llega a Arequipa con su gira 2025, prometiendo una noche llena de baladas y éxitos que han marcado su carrera.",
    "coordinates": [-71.535736, -16.3999] 
  }
]